aletheia_genetic_optimizers/__init__.py
aletheia_genetic_optimizers/bounds/__init__.py
aletheia_genetic_optimizers/genetic_optimizer/__init__.py
aletheia_genetic_optimizers/individuals/__init__.py
aletheia_genetic_optimizers/mutation_methods/__init__.py
aletheia_genetic_optimizers/population_methods/__init__.py
aletheia_genetic_optimizers/reproduction_methods/__init__.py
aletheia_genetic_optimizers/tournament_methods/__init__.py
aletheia_genetic_optimizers/variability_explossion_methods/__init__.py
aletheia_genetic_optimizers-2.2.1.dist-info/METADATA
aletheia_genetic_optimizers-2.2.1.dist-info/WHEEL
aletheia_genetic_optimizers-2.2.1.dist-info/top_level.txt
aletheia_genetic_optimizers-2.2.1.dist-info/RECORD
